{
  "source_root": "C:/Users/santo/Documents/OpenGunz/ogz-client-master/Maps",
  "map": "prison II",
  "count_files": 1,
  "files": [
    {
      "file": "C:\\Users\\santo\\Documents\\OpenGunz\\ogz-client-master\\Maps\\prison II\\spawn.xml",
      "count": 6,
      "spawns": [
        {
          "item": "bullet02",
          "timesec": "45000",
          "gametype": "solo",
          "pos": [
            1867.5767822,
            -6487.0117188,
            -649.8615723
          ]
        },
        {
          "item": "ap03",
          "timesec": "45000",
          "gametype": "solo",
          "pos": [
            2993.03125,
            4084.5275879,
            -246.7167664
          ]
        },
        {
          "item": "hp03",
          "timesec": "45000",
          "gametype": "solo",
          "pos": [
            0.0,
            -1.5e-06,
            3.2833252
          ]
        },
        {
          "item": "hp02",
          "timesec": "30000",
          "gametype": "solo",
          "pos": [
            102.1681519,
            -6487.0117188,
            -649.8615723
          ]
        },
        {
          "item": "bullet02",
          "timesec": "45000",
          "gametype": "team",
          "pos": [
            -1130.6702881,
            -4191.2607422,
            3.2832642
          ]
        },
        {
          "item": "bullet02",
          "timesec": "45000",
          "gametype": "team",
          "pos": [
            -1376.5926514,
            4180.6269531,
            3.2832642
          ]
        }
      ],
      "source_root": "C:/Users/santo/Documents/OpenGunz/ogz-client-master/Maps",
      "relative": "prison II/spawn.xml"
    }
  ]
}